cachedisk/__init__.py
cachedisk/core.py
cachedisk-0.4.dist-info/LICENSE
cachedisk-0.4.dist-info/METADATA
cachedisk-0.4.dist-info/WHEEL
cachedisk-0.4.dist-info/top_level.txt
cachedisk-0.4.dist-info/RECORD
